[
  {
    "listing": "/exercises.html",
    "items": [
      "/exercises/linux_shell.html",
      "/exercises/slurm_and_the_cluster.html",
      "/exercises/power.html",
      "/exercises/data_viz.html"
    ]
  },
  {
    "listing": "/homework.html",
    "items": [
      "/homework/hw1_shell_and_linux.html",
      "/homework/hw2_slurm_and_cluster.html",
      "/homework/hw3_study_planning.html",
      "/homework/hw4_R_package.html",
      "/homework/hw5_grant_writing.html",
      "/homework/hw6_app.html",
      "/homework/presentation1.html",
      "/homework/presentation2.html",
      "/homework/term2_hw1_prediction.html",
      "/homework/nhanes_project.html"
    ]
  },
  {
    "listing": "/resources.html",
    "items": [
      "/resources/missing_data_lecture.html"
    ]
  }
]